tpm2_native
