Metadata-Version: 2.1
Name: tpm2-native
Version: 5
Summary: collection of tools for playing with TPM v2 modules natively e.g. through SPI
Home-page: https://github.com/metebalci/tpm2-native
Author: Mete Balci
Author-email: metebalci@gmail.com
License: GPLv3
Keywords: tpm,tpm2
Platform: UNKNOWN
Classifier: Development Status :: 3 - Alpha
Classifier: Environment :: Console
Classifier: License :: OSI Approved :: GNU General Public License v3 (GPLv3)
Classifier: Programming Language :: Python :: 3
Classifier: License :: OSI Approved :: MIT License
Classifier: Operating System :: OS Independent
Classifier: Topic :: Utilities
